{"background_image": "images/collection/pe2018/web/08_back.jpg", "data": [{"src": "images/collection/pe2018/web/01.jpg", "alt": "Vestito Hanami"}, {"src": "images/collection/pe2018/web/02.jpg", "alt": "Vestito Hanami"}, {"src": "images/collection/pe2018/web/03.jpg", "alt": "Vestito Hanami"}, {"src": "images/collection/pe2018/web/04.jpg", "alt": "Vestito Hanami"}, {"src": "images/collection/pe2018/web/05.jpg", "alt": "Vestito Hanami"}, {"src": "images/collection/pe2018/web/06.jpg", "alt": "Vestito Hanami"}, {"src": "images/collection/pe2018/web/07.jpg", "alt": "Vestito Hanami"}, {"src": "images/collection/pe2018/web/08.jpg", "alt": "Vestito Hanami"}, {"src": "images/collection/pe2018/web/09.jpg", "alt": "Vestito Hanami"}, {"src": "images/collection/pe2018/web/10.jpg", "alt": "Vestito Hanami"}, {"src": "images/collection/pe2018/web/11.jpg", "alt": "Vestito Hanami"}, {"src": "images/collection/pe2018/web/12.jpg", "alt": "Vestito Hanami"}, {"src": "images/collection/pe2018/web/13.jpg", "alt": "Vestito Hanami"}, {"src": "images/collection/pe2018/web/14.jpg", "alt": "Vestito Hanami"}, {"src": "images/collection/pe2018/web/15.jpg", "alt": "Vestito Hanami"}, {"src": "images/collection/pe2018/web/16.jpg", "alt": "Vestito Hanami"}, {"src": "images/collection/pe2018/web/17.jpg", "alt": "Vestito Hanami"}, {"src": "images/collection/pe2018/web/18.jpg", "alt": "Vestito Hanami"}, {"src": "images/collection/pe2018/web/19.jpg", "alt": "Vestito Hanami"}, {"src": "images/collection/pe2018/web/20.jpg", "alt": "Vestito Hanami"}, {"src": "images/collection/pe2018/web/21.jpg", "alt": "Vestito Hanami"}, {"src": "images/collection/pe2018/web/22.jpg", "alt": "Vestito Hanami"}, {"src": "images/collection/pe2018/web/23.jpg", "alt": "Vestito Hanami"}, {"src": "images/collection/pe2018/web/24.jpg", "alt": "Vestito Hanami"}, {"src": "images/collection/pe2018/web/25.jpg", "alt": "Vestito Hanami"}, {"src": "images/collection/pe2018/web/26.jpg", "alt": "Vestito Hanami"}, {"src": "images/collection/pe2018/web/27.jpg", "alt": "Vestito Hanami"}, {"src": "images/collection/pe2018/web/28.jpg", "alt": "Vestito Hanami"}, {"src": "images/collection/pe2018/web/29.jpg", "alt": "Vestito Hanami"}, {"src": "images/collection/pe2018/web/30.jpg", "alt": "Vestito Hanami"}, {"src": "images/collection/pe2018/web/31.jpg", "alt": "Vestito Hanami"}, {"src": "images/collection/pe2018/web/32.jpg", "alt": "Vestito Hanami"}, {"src": "images/collection/pe2018/web/33.jpg", "alt": "Vestito Hanami"}, {"src": "images/collection/pe2018/web/34.jpg", "alt": "Vestito Hanami"}, {"src": "images/collection/pe2018/web/35.jpg", "alt": "Vestito Hanami"}, {"src": "images/collection/pe2018/web/36.jpg", "alt": "Vestito Hanami"}, {"src": "images/collection/pe2018/web/37.jpg", "alt": "Vestito Hanami"}, {"src": "images/collection/pe2018/web/38.jpg", "alt": "Vestito Hanami"}, {"src": "images/collection/pe2018/web/39.jpg", "alt": "Vestito Hanami"}, {"src": "images/collection/pe2018/web/40.jpg", "alt": "Vestito Hanami"}, {"src": "images/collection/pe2018/web/41.jpg", "alt": "Vestito Hanami"}, {"src": "images/collection/pe2018/web/42.jpg", "alt": "Vestito Hanami"}, {"src": "images/collection/pe2018/web/43.jpg", "alt": "Vestito Hanami"}, {"src": "images/collection/pe2018/web/44.jpg", "alt": "Vestito Hanami"}, {"src": "images/collection/pe2018/web/45.jpg", "alt": "Vestito Hanami"}, {"src": "images/collection/pe2018/web/46.jpg", "alt": "Vestito Hanami"}, {"src": "images/collection/pe2018/web/47.jpg", "alt": "Vestito Hanami"}, {"src": "images/collection/pe2018/web/48.jpg", "alt": "Vestito Hanami"}], "title": "Spring Summer 2018"}
